damiao_motor/__init__.py
damiao_motor/_version.py
damiao_motor/cli/__init__.py
damiao_motor/cli/commands.py
damiao_motor/cli/display.py
damiao_motor/cli/formatter.py
damiao_motor/core/__init__.py
damiao_motor/core/controller.py
damiao_motor/core/motor.py
damiao_motor/gui/__init__.py
damiao_motor/gui/web_gui.py
damiao_motor/gui/static/css/style.css
damiao_motor/gui/static/js/app.js
damiao_motor/gui/templates/index.html
damiao_motor-1.0.4.dist-info/METADATA
damiao_motor-1.0.4.dist-info/WHEEL
damiao_motor-1.0.4.dist-info/entry_points.txt
damiao_motor-1.0.4.dist-info/top_level.txt
damiao_motor-1.0.4.dist-info/RECORD
