Metadata-Version: 2.4
Name: damiao-motor
Version: 1.0.4
Summary: Python driver for DaMiao motors
Author-email: jia <jiaxiejason@gmail.com>
License: MIT
Project-URL: Homepage, https://github.com/jia-xie/python-damiao-driver
Project-URL: Repository, https://github.com/jia-xie/python-damiao-driver
Keywords: damiao,motor,can,robotics
Requires-Python: >=3.8
Requires-Dist: python-can<5.0,>=4.3
Requires-Dist: flask<4.0,>=3.0
